captif_cpx_config/__init__.py
captif_cpx_config/metadata.py
captif_cpx_config-1.0.0.dist-info/LICENSE
captif_cpx_config-1.0.0.dist-info/METADATA
captif_cpx_config-1.0.0.dist-info/WHEEL
captif_cpx_config-1.0.0.dist-info/RECORD
