Metadata-Version: 2.1
Name: captif-cpx-config
Version: 1.0.0
Summary: 
License: MIT
Author: John Bull
Author-email: john.bull@nzta.govt.nz
Requires-Python: >=3.9,<4.0
Classifier: License :: OSI Approved :: MIT License
Classifier: Programming Language :: Python :: 3
Classifier: Programming Language :: Python :: 3.9
Classifier: Programming Language :: Python :: 3.10
Classifier: Programming Language :: Python :: 3.11
Requires-Dist: pydantic (>=1.10.8,<2.0.0)
